MANIFEST.in
README.md
setup.py
sample/0.5p_tfe.pdb
sample/0p_tfe.pdb
sample/17p_tfe.pdb
sample/25p_tfe.pdb
sample/50p_tfe.pdb
sample/blendrc
sample/tfe.pdb
sample/water.pdb
src/blendpdb/__init__.py
src/blendpdb/blendpdb.py
src/blendpdb.egg-info/PKG-INFO
src/blendpdb.egg-info/SOURCES.txt
src/blendpdb.egg-info/dependency_links.txt
src/blendpdb.egg-info/entry_points.txt
src/blendpdb.egg-info/requires.txt
src/blendpdb.egg-info/top_level.txt
src/blendpdb.egg-info/zip-safe