Metadata-Version: 1.1
Name: blendpdb
Version: 0.1.2
Summary: Blending two PDB files to create solvate
Home-page: https://github.com/lambdalisue/blendpdb
Author: Alisue
Author-email: lambdalisue@hashnote.net
License: MIT
Download-URL: https://github.com/lambdalisue/blendpdb/tarball/master
Keywords: blend,pdb,solvate
Platform: UNKNOWN
Classifier: Intended Audience :: Developers
Classifier: License :: OSI Approved :: MIT License
Classifier: Programming Language :: Python
